nsip_skills/__init__.py
nsip_skills/ancestry_builder.py
nsip_skills/ebv_analysis.py
nsip_skills/flock_import.py
nsip_skills/flock_stats.py
nsip_skills/inbreeding.py
nsip_skills/mating_optimizer.py
nsip_skills/progeny_analysis.py
nsip_skills/recommendation_engine.py
nsip_skills/selection_index.py
nsip_skills/trait_planner.py
nsip_skills/common/__init__.py
nsip_skills/common/data_models.py
nsip_skills/common/formatters.py
nsip_skills/common/nsip_wrapper.py
nsip_skills/common/spreadsheet_io.py
nsip_skills-1.4.7.dist-info/METADATA
nsip_skills-1.4.7.dist-info/WHEEL
nsip_skills-1.4.7.dist-info/entry_points.txt
nsip_skills-1.4.7.dist-info/RECORD
