Metadata-Version: 2.4
Name: nsip-skills
Version: 1.4.7
Summary: Breeding decision support tools for sheep genetics using NSIP EBV data
Project-URL: Homepage, https://github.com/epicpast/nsip-api-client
Project-URL: Documentation, https://github.com/epicpast/nsip-api-client/blob/main/docs/nsip-skills.md
Project-URL: Repository, https://github.com/epicpast/nsip-api-client.git
Project-URL: Bug Tracker, https://github.com/epicpast/nsip-api-client/issues
Project-URL: Releases, https://github.com/epicpast/nsip-api-client/releases
Author-email: Robert Allen <bob@epicpastures.com>
License: MIT
Keywords: breeding,ebv,genetics,inbreeding,livestock,nsip,selection-index,sheep
Classifier: Development Status :: 4 - Beta
Classifier: Intended Audience :: Developers
Classifier: Intended Audience :: Science/Research
Classifier: License :: OSI Approved :: MIT License
Classifier: Programming Language :: Python :: 3
Classifier: Programming Language :: Python :: 3.12
Classifier: Programming Language :: Python :: 3.13
Classifier: Topic :: Scientific/Engineering
Classifier: Topic :: Scientific/Engineering :: Bio-Informatics
Classifier: Topic :: Software Development :: Libraries :: Python Modules
Requires-Python: >=3.12
Requires-Dist: nsip-client<2.0.0,>=1.4.7
Requires-Dist: numpy>=1.24.0
Requires-Dist: openpyxl>=3.1.0
Requires-Dist: pandas>=2.0.0
Provides-Extra: gsheets
Requires-Dist: gspread>=5.10.0; extra == 'gsheets'
